napari_dv/__init__.py
napari_dv/_reader.py
napari_dv/_version.py
napari_dv/_writer.py
napari_dv/napari.yaml
napari_dv/_tests/test_reader.py
napari_dv/_tests/test_writer.py
napari_dv/_tests/toxo.dv
napari_dv-0.3.0.dist-info/LICENSE
napari_dv-0.3.0.dist-info/METADATA
napari_dv-0.3.0.dist-info/WHEEL
napari_dv-0.3.0.dist-info/entry_points.txt
napari_dv-0.3.0.dist-info/top_level.txt
napari_dv-0.3.0.dist-info/RECORD
