Metadata-Version: 2.1
Name: napari-dv
Version: 0.3.0
Summary: Deltavision/MRC file reader for napari
Home-page: https://github.com/tlambert03/napari-dv
Author: Talley Lambert
Author-email: talley.lambert@gmail.com
License: MIT
Project-URL: Bug Tracker, https://github.com/tlambert03/napari-dv/issues
Project-URL: Documentation, https://github.com/tlambert03/napari-dv#README.md
Project-URL: Source Code, https://github.com/tlambert03/napari-dv
Project-URL: User Support, https://github.com/tlambert03/napari-dv/issues
Platform: UNKNOWN
Classifier: Development Status :: 4 - Beta
Classifier: Framework :: napari
Classifier: Intended Audience :: Developers
Classifier: License :: OSI Approved :: MIT License
Classifier: Operating System :: OS Independent
Classifier: Programming Language :: Python
Classifier: Programming Language :: Python :: 3
Classifier: Programming Language :: Python :: 3 :: Only
Classifier: Programming Language :: Python :: 3.7
Classifier: Programming Language :: Python :: 3.8
Classifier: Programming Language :: Python :: 3.9
Classifier: Programming Language :: Python :: 3.10
Requires-Python: >=3.7
License-File: LICENSE
Requires-Dist: mrc (>=0.2.0)
Requires-Dist: napari-plugin-engine (>=0.1.4)
Provides-Extra: testing
Requires-Dist: numpy ; extra == 'testing'
Requires-Dist: pytest ; extra == 'testing'
Requires-Dist: pytest-cov ; extra == 'testing'
